<?xml version = '1.0' encoding = 'UTF-8'?>
<!-- dbdrv: exec java oracle/jrad/tools/xml/importer XMLImporter.class java &phase=dat+24 checkfile:~PROD:~PATH:~FILE &fullpath_~PROD_~PATH_~FILE -username &un_apps -password &pw_apps -dbconnection &jdbc_db_addr  -userId "1" -rootPackage /oracle/apps/~PROD  -rootdir &fullpath_~PROD_mds_directory -->
<oa:listOfValues title="Toolbox Suppliers LOV" amDefName="oracle.apps.fnd.framework.toolbox.lov.server.TutorialLOVAM" xmlns="http://xmlns.oracle.com/jrad" xmlns:oa="http://xmlns.oracle.com/oa" xmlns:ui="http://xmlns.oracle.com/uix/ui" xmlns:user="http://xmlns.oracle.com/jrad/user" xml:lang="en-US" version="9.0.3.8.6_865" file-version="$Header: SuppliersLovRN.xml 120.8 2006/05/25 13:12:49 atgops1 noship $" scope="/">
   <ui:contents>
      <oa:table akRegionCode="FWK_TBX_T_SUPPLIERS_LOV" regionName="Suppliers Table" blockSize="25" standalone="true" id="SuppliersTable" name="FWK_TBX_T_SUPPLIERS_LOV" shortDesc="Suppliers Table">
         <ui:contents>
            <oa:messageStyledText queryable="true" viewName="SuppliersLOVVO1" viewAttr="Name" id="SupplierName" prompt="Supplier"/>
            <oa:messageStyledText prompt="On Hold" viewName="SuppliersLOVVO1" viewAttr="OnHoldDisplay" id="OnHoldDisplay" promptTranslationExpansion="none"/>
            <oa:formValue viewName="SuppliersLOVVO1" viewAttr="SupplierId" id="SupplierId" prompt="Supplier Number" dataType="NUMBER" rendered="true"/>
         </ui:contents>
      </oa:table>
   </ui:contents>
</oa:listOfValues>
